odoo/addons/l10n_es_mis_report/README.rst
odoo/addons/l10n_es_mis_report/__init__.py
odoo/addons/l10n_es_mis_report/__manifest__.py
odoo/addons/l10n_es_mis_report/data/mis_report_balance_abreviated.xml
odoo/addons/l10n_es_mis_report/data/mis_report_balance_normal.xml
odoo/addons/l10n_es_mis_report/data/mis_report_balance_sme.xml
odoo/addons/l10n_es_mis_report/data/mis_report_pyg_abreviated.xml
odoo/addons/l10n_es_mis_report/data/mis_report_pyg_normal.xml
odoo/addons/l10n_es_mis_report/data/mis_report_pyg_sme.xml
odoo/addons/l10n_es_mis_report/data/mis_report_revenues_expenses_normal.xml
odoo/addons/l10n_es_mis_report/data/mis_report_styles.xml
odoo11_addon_l10n_es_mis_report-11.0.2.2.0.dist-info/DESCRIPTION.rst
odoo11_addon_l10n_es_mis_report-11.0.2.2.0.dist-info/METADATA
odoo11_addon_l10n_es_mis_report-11.0.2.2.0.dist-info/RECORD
odoo11_addon_l10n_es_mis_report-11.0.2.2.0.dist-info/WHEEL
odoo11_addon_l10n_es_mis_report-11.0.2.2.0.dist-info/metadata.json
odoo11_addon_l10n_es_mis_report-11.0.2.2.0.dist-info/top_level.txt
